a8logging/a8logging.py
a8logging-1.0.6.dist-info/LICENSE.md
a8logging-1.0.6.dist-info/METADATA
a8logging-1.0.6.dist-info/WHEEL
a8logging-1.0.6.dist-info/top_level.txt
a8logging-1.0.6.dist-info/RECORD
